bagel/__init__.py
bagel/_version.py
bagel/bids_table_model.py
bagel/cli.py
bagel/dictionary_models.py
bagel/logger.py
bagel/mappings.py
bagel/models.py
bagel/utilities/__init__.py
bagel/utilities/bids_utils.py
bagel/utilities/derivative_utils.py
bagel/utilities/file_utils.py
bagel/utilities/model_utils.py
bagel/utilities/pheno_utils.py
bagel-0.10.0.dist-info/METADATA
bagel-0.10.0.dist-info/WHEEL
bagel-0.10.0.dist-info/entry_points.txt
bagel-0.10.0.dist-info/licenses/LICENSE
bagel-0.10.0.dist-info/RECORD
