Metadata-Version: 2.4
Name: bagel
Version: 0.10.0
Summary: Automatic parsing of subjects' tabular data and imaging metadata into Neurobagel graph-compatible JSONLD files.
Author: Neurobagel Developers
Maintainer-email: Sebastian Urchs <sebastian.urchs@mcgill.ca>
License: MIT License
License-File: LICENSE
Classifier: Development Status :: 1 - Planning
Classifier: Intended Audience :: Science/Research
Classifier: License :: OSI Approved :: MIT License
Classifier: Programming Language :: Python :: 3.11
Requires-Python: >=3.11
Requires-Dist: bids2table
Requires-Dist: httpx
Requires-Dist: isodate
Requires-Dist: jsonschema
Requires-Dist: pandera[pandas]
Requires-Dist: pybids
Requires-Dist: pydantic<3,>=2
Requires-Dist: rich
Requires-Dist: typer
Provides-Extra: dev
Requires-Dist: coverage; extra == 'dev'
Requires-Dist: pre-commit; extra == 'dev'
Requires-Dist: pytest; extra == 'dev'
Provides-Extra: test
Requires-Dist: coverage; extra == 'test'
Requires-Dist: pytest; extra == 'test'
